{"hints": [{"replace": false, "widgets": {}, "content": "We can break apart the number $\\blueE{22}$ by place value.\n\n$\\begin{align}\n&\\maroonD{8}+\\blueE{22}\\\\\\\\\n=&\\maroonD8 + (\\blueE{20} + \\blueE{2})\n\\end{align}$", "images": {}}, {"replace": false, "widgets": {}, "content": "Next, we can shift the parentheses to be around the $\\maroonD8+ \\blueE2$.\n\n$\\begin{align}\n&\\maroonD{8}+\\blueE{22}\\\\\\\\\n=&\\maroonD8 + (\\blueE{20} + \\blueE{2})\\\\\\\\\n=&(\\maroonD{8}+ \\blueE2)+\\blueE{20}\n\\end{align}$", "images": {}}, {"replace": false, "widgets": {}, "content": "Now, lets add $\\maroonD8+ \\blueE2$.\n\n$\\begin{align}\n&\\maroonD{8}+\\blueE{22}\\\\\\\\\n=&\\maroonD8 + (\\blueE{20} + \\blueE{2})\\\\\\\\\n=&(\\maroonD{8}+ \\blueE2)+\\blueE{20}\\\\\\\\\n=&\\purpleD{10} + \\blueE{20}\n\\end{align}$", "images": {}}, {"replace": false, "widgets": {}, "content": "Last, let's add $\\purpleE{10} + \\blueE{20}$.\n\n$\\begin{align}\n&\\maroonD{8}+\\blueE{22}\\\\\\\\\n=&\\maroonD8 + (\\blueE{20} + \\blueE{2})\\\\\\\\\n=&(\\maroonD{8}+ \\blueE2)+\\blueE{20}\\\\\\\\\n=&\\purpleD{10} + \\blueE{20}\\\\\\\\\n=&\\goldE{30}\n\\end{align}$", "images": {}}, {"replace": false, "widgets": {}, "content": "Here is completed set of equations:\n\n$\\begin{align}\n&\\maroonD{8}+\\blueE{22}\\\\\\\\\n=&\\maroonD8 + (\\blueE{20} + \\blueE{2})\\\\\\\\\n=&(\\maroonD{8}+ \\blueE2)+\\blueE{20}\\\\\\\\\n=&\\purpleD{10} + \\blueE{20}\\\\\\\\\n=&\\goldE{30}\n\\end{align}$", "images": {}}], "answerArea": {"calculator": false, "periodicTable": false, "chi2Table": false, "zTable": false, "tTable": false}, "question": {"widgets": {"numeric-input 5": {"options": {"multipleNumberInput": false, "coefficient": false, "static": false, "answers": [{"strict": false, "value": 2, "status": "correct", "maxError": null, "simplify": "required", "message": ""}], "size": "small", "rightAlign": false, "labelText": ""}, "graded": true, "version": {"minor": 0, "major": 0}, "static": false, "alignment": "default", "type": "numeric-input"}, "numeric-input 8": {"options": {"multipleNumberInput": false, "coefficient": false, "static": false, "answers": [{"strict": false, "value": 30, "status": "correct", "maxError": null, "simplify": "required", "message": ""}], "size": "small", "rightAlign": false, "labelText": ""}, "graded": true, "version": {"minor": 0, "major": 0}, "static": false, "alignment": "default", "type": "numeric-input"}, "numeric-input 6": {"options": {"multipleNumberInput": false, "coefficient": false, "static": false, "answers": [{"strict": false, "value": 2, "status": "correct", "maxError": null, "simplify": "required", "message": ""}], "size": "small", "rightAlign": false, "labelText": ""}, "graded": true, "version": {"minor": 0, "major": 0}, "static": false, "alignment": "default", "type": "numeric-input"}, "numeric-input 7": {"options": {"multipleNumberInput": false, "coefficient": false, "static": false, "answers": [{"strict": false, "value": 10, "status": "correct", "maxError": null, "simplify": "required", "message": ""}], "size": "small", "rightAlign": false, "labelText": ""}, "graded": true, "version": {"minor": 0, "major": 0}, "static": false, "alignment": "default", "type": "numeric-input"}}, "content": "**Complete to solve $8 + 22$.**\n\n$\\maroonD{8}+\\blueE{22}$ | \n- | - \n$=\\maroonD{8}~+($ [[☃ numeric-input 5]] $+~ \\blueE{20})$|\n$=(\\maroonD{8} ~+~$ [[☃ numeric-input 6]] $ )+~\\blueE{20}$ | \n$=$ [[☃ numeric-input 7]] $+~\\blueE{20}$| \n$=$ [[☃ numeric-input 8]] |", "images": {}}, "itemDataVersion": {"minor": 1, "major": 0}}
