{"hints": [{"widgets": {}, "content": "$4+1=\\green5$\n\n![](${☣ LOCALPATH}/images/b2e284977d203578b7fb3b1124cbd867.png) ![](${☣ LOCALPATH}/images/bc356e4561ed38af21e6a00d50a669b7.png)", "images": {"${☣ LOCALPATH}/images/bc356e4561ed38af21e6a00d50a669b7.png": {"width": 200, "height": 163}, "${☣ LOCALPATH}/images/b2e284977d203578b7fb3b1124cbd867.png": {"width": 200, "height": 163}}}, {"widgets": {}, "content": "There are $\\green5$ crayons in all.", "images": {}}], "answerArea": {"periodicTable": false, "options": {"widgets": {}, "content": "", "images": {}}, "tTable": false, "calculator": false, "type": "multiple", "chi2Table": false, "zTable": false}, "question": {"widgets": {"input-number 1": {"options": {"value": 5, "inexact": false, "maxError": 0.1, "size": "small", "simplify": "required", "answerType": "number"}, "graded": true, "version": {"minor": 0, "major": 0}, "static": false, "alignment": "default", "type": "input-number"}}, "content": "$4$ crayons $+$ $1$ crayon $=$ [[☃ input-number 1]] crayons\n\n![](${☣ LOCALPATH}/images/0f91d53ed470aebf29300d4c3c22cf10.png) ![](${☣ LOCALPATH}/images/22819c0ae75bfb59e1d591a51ec26e54.png)", "images": {"${☣ LOCALPATH}/images/22819c0ae75bfb59e1d591a51ec26e54.png": {"width": 200, "height": 163}, "${☣ LOCALPATH}/images/0f91d53ed470aebf29300d4c3c22cf10.png": {"width": 200, "height": 163}}}, "itemDataVersion": {"minor": 1, "major": 0}}
