{"hints": [{"widgets": {}, "content": "Count $1, 2, 3, 4, 5$.  \nDrag a piece of cheese into the box for each number. \n\n![](${☣ LOCALPATH}/images/2c304149be81530878b58137b70f44a0.jpg)  \n$\\qquad\\:\\:\\: 1 \\qquad\\quad\\:\\: 2 \\qquad\\quad\\:\\: 3 \\qquad\\quad\\:\\: 4 \\qquad\\quad\\:\\: 5$", "images": {"${☣ LOCALPATH}/images/2c304149be81530878b58137b70f44a0.jpg": {"width": 386, "height": 113}}}], "answerArea": {"calculator": false, "options": {"widgets": {}, "content": "", "images": {}}, "type": "multiple"}, "question": {"widgets": {"orderer 1": {"options": {"options": [{"content": "![](${☣ LOCALPATH}/images/3c24410be1350d01149021359270f477.png)"}], "correctOptions": [{"content": "![](${☣ LOCALPATH}/images/3c24410be1350d01149021359270f477.png)"}, {"content": "![](${☣ LOCALPATH}/images/3c24410be1350d01149021359270f477.png)"}, {"content": "![](${☣ LOCALPATH}/images/3c24410be1350d01149021359270f477.png)"}, {"content": "![](${☣ LOCALPATH}/images/3c24410be1350d01149021359270f477.png)"}, {"content": "![](${☣ LOCALPATH}/images/3c24410be1350d01149021359270f477.png)"}], "height": "auto", "otherOptions": [], "layout": "horizontal"}, "type": "orderer", "graded": true, "version": {"minor": 0, "major": 0}}}, "content": "**Put $5$ pieces of cheese in the box.**\n\n[[☃ orderer 1]]", "images": {}}, "itemDataVersion": {"minor": 1, "major": 0}}
