{"hints": [{"widgets": {}, "content": "$9$, $10$, $11$, $\\blue{12}$\n\nThe first missing number is $\\blue{12}$.\n\n\n", "images": {}}, {"widgets": {}, "content": "$9$, $10$, $11$, $\\blue{12}$,  $13$, $14$, $15$, $\\green{16}$  \n\n\n", "images": {}}, {"widgets": {}, "content": "The missing numbers are $\\blue{12}$ and $\\green{16}$.", "images": {}}], "answerArea": {"calculator": false, "options": {"widgets": {}, "content": "", "images": {}}, "type": "multiple"}, "question": {"widgets": {"input-number 2": {"options": {"value": 16, "inexact": false, "maxError": 0.1, "size": "small", "simplify": "required", "answerType": "number"}, "type": "input-number", "graded": true, "version": {"minor": 0, "major": 0}}, "input-number 1": {"options": {"value": 12, "inexact": false, "maxError": 0.1, "size": "small", "simplify": "required", "answerType": "number"}, "type": "input-number", "graded": true, "version": {"minor": 0, "major": 0}}}, "content": "**Type the missing numbers in the boxes.**\n\n$9$, $10$, $11$, [[☃ input-number 1]], $13$, $14$, $15$, [[☃ input-number 2]]", "images": {"${☣ LOCALPATH}/images/58b1a0ea26499d43f3d57cad21508351.png": {"width": 100, "height": 30}}}, "itemDataVersion": {"minor": 1, "major": 0}}
