{"hints": [{"widgets": {}, "content": "![](${☣ LOCALPATH}/images/2bd5e35af5e34bd5c5736b955be9fcc0.png)", "images": {"${☣ LOCALPATH}/images/2bd5e35af5e34bd5c5736b955be9fcc0.png": {"width": 400, "height": 358}}}, {"widgets": {}, "content": "$\\green{\\text{Horses}}+\\pink{8}=\\purple{\\text{Elephants}}$\n\n$\\green{7} + \\pink{8} =\\purple\\Box$\n\n![](${☣ LOCALPATH}/images/416c69fee3099c33ff305ae2f5d19f08.png)", "images": {"${☣ LOCALPATH}/images/416c69fee3099c33ff305ae2f5d19f08.png": {"width": 400, "height": 317}}}, {"widgets": {}, "content": "There are $\\purple{15}$ elephants.", "images": {}}], "answerArea": {"calculator": false, "options": {"widgets": {}, "content": "", "images": {}}, "type": "multiple"}, "question": {"widgets": {"input-number 1": {"options": {"value": 15, "inexact": false, "maxError": 0.1, "size": "normal", "simplify": "required", "answerType": "number"}, "type": "input-number", "graded": true, "version": {"minor": 0, "major": 0}}}, "content": "There are $7$ horses in the circus.\n\nThere are $8$ more elephants than horses in the circus.\n\n**How many elephants are in the circus?**\n\n[[☃ input-number 1]] elephants", "images": {"${☣ LOCALPATH}/images/2bd5e35af5e34bd5c5736b955be9fcc0.png": {"width": 400, "height": 358}}}, "itemDataVersion": {"minor": 1, "major": 0}}
