{"hints": [{"replace": false, "widgets": {}, "content": "$10$ can be separated into two parts:  $\\red{5}$ and $\\green?$ \n\n", "images": {"${☣ LOCALPATH}/images/5db84fe5a479fc7d26270e68480b916d.png": {"width": 400, "height": 60}}}, {"replace": false, "widgets": {}, "content": "We can use subtraction to find the missing part: $10 - \\red{5} = \\green5$\n\nWe can also think about how much more can be added to $\\red{5}$ to get $10$: $\\red{5} + \\green5 = 10$\n\n![](${☣ LOCALPATH}/images/5db84fe5a479fc7d26270e68480b916d.png)", "images": {"${☣ LOCALPATH}/images/5db84fe5a479fc7d26270e68480b916d.png": {"width": 400, "height": 60}}}, {"replace": false, "widgets": {}, "content": "The answer \n\n$ 10 - \\red{5} = \\green5 $\n\n$\\red{5} + \\green5 = 10$", "images": {}}], "answerArea": {"calculator": false, "periodicTable": false, "chi2Table": false, "zTable": false, "tTable": false}, "question": {"widgets": {"input-number 2": {"options": {"value": 5, "inexact": false, "maxError": 0.1, "size": "small", "simplify": "required", "answerType": "number"}, "graded": true, "version": {"minor": 0, "major": 0}, "static": false, "alignment": "default", "type": "input-number"}, "input-number 1": {"options": {"value": 5, "inexact": false, "maxError": 0.1, "size": "small", "simplify": "required", "answerType": "number"}, "graded": true, "version": {"minor": 0, "major": 0}, "static": false, "alignment": "default", "type": "input-number"}}, "content": "There are $10$ wizards living in the magic castle. $5$ of the wizards wear capes and the rest do not.\n\n\n**Complete the number sentences to find how many wizards do not wear capes.**\n\n$10$ wizards in total $ - \\,5$ with capes $= $ [[☃ input-number 2]] without capes\n\n$5$ with capes $ + $  [[☃ input-number 1]] without capes $ = 10$ wizards in total\n", "images": {"${☣ LOCALPATH}/images/4f59b4c04da1bd4b3a80ac568f5c84f7.png": {"width": 400, "height": 60}}}, "itemDataVersion": {"minor": 1, "major": 0}}
